chronos/__init__.py
chronos/datetime_filter.py
chronos/types.py
python_chronos-0.2.0.dist-info/LICENSE
python_chronos-0.2.0.dist-info/METADATA
python_chronos-0.2.0.dist-info/WHEEL
python_chronos-0.2.0.dist-info/top_level.txt
python_chronos-0.2.0.dist-info/RECORD
